eidolon_ai_sdk/__init__.py
eidolon_ai_sdk/agent/__init__.py
eidolon_ai_sdk/agent/agent.py
eidolon_ai_sdk/agent/api_agent.py
eidolon_ai_sdk/agent/audio_agent.py
eidolon_ai_sdk/agent/browser/__init__.py
eidolon_ai_sdk/agent/browser/scraping_agent.py
eidolon_ai_sdk/agent/browser/search_agent.py
eidolon_ai_sdk/agent/browser/web_researcher.py
eidolon_ai_sdk/agent/deprecated.py
eidolon_ai_sdk/agent/doc_manager/__init__.py
eidolon_ai_sdk/agent/doc_manager/document_manager.py
eidolon_ai_sdk/agent/doc_manager/document_processor.py
eidolon_ai_sdk/agent/doc_manager/loaders/__init__.py
eidolon_ai_sdk/agent/doc_manager/loaders/azure_loader.py
eidolon_ai_sdk/agent/doc_manager/loaders/base_loader.py
eidolon_ai_sdk/agent/doc_manager/loaders/filesystem_loader.py
eidolon_ai_sdk/agent/doc_manager/loaders/github_loader.py
eidolon_ai_sdk/agent/doc_manager/loaders/memorywrapper_loader.py
eidolon_ai_sdk/agent/doc_manager/loaders/s3_loader.py
eidolon_ai_sdk/agent/doc_manager/parsers/__init__.py
eidolon_ai_sdk/agent/doc_manager/parsers/auto_parser.py
eidolon_ai_sdk/agent/doc_manager/parsers/base_parser.py
eidolon_ai_sdk/agent/doc_manager/parsers/code_ast_parsers/__init__.py
eidolon_ai_sdk/agent/doc_manager/parsers/code_ast_parsers/base_ast_generator.py
eidolon_ai_sdk/agent/doc_manager/parsers/code_ast_parsers/cobol.py
eidolon_ai_sdk/agent/doc_manager/parsers/code_ast_parsers/javascript.py
eidolon_ai_sdk/agent/doc_manager/parsers/code_ast_parsers/programing_language_parser.py
eidolon_ai_sdk/agent/doc_manager/parsers/code_ast_parsers/python.py
eidolon_ai_sdk/agent/doc_manager/parsers/ms_word_parser.py
eidolon_ai_sdk/agent/doc_manager/parsers/pdf_parsers.py
eidolon_ai_sdk/agent/doc_manager/parsers/text_parsers.py
eidolon_ai_sdk/agent/doc_manager/transformer/__init__.py
eidolon_ai_sdk/agent/doc_manager/transformer/auto_transformer.py
eidolon_ai_sdk/agent/doc_manager/transformer/document_transformer.py
eidolon_ai_sdk/agent/doc_manager/transformer/text_splitters.py
eidolon_ai_sdk-0.1.184.dist-info/METADATA
eidolon_ai_sdk-0.1.184.dist-info/WHEEL
eidolon_ai_sdk-0.1.184.dist-info/entry_points.txt
eidolon_ai_sdk-0.1.184.dist-info/RECORD
